loggerr/__init__.py
loggerr-1.1.0.dist-info/LICENSE
loggerr-1.1.0.dist-info/METADATA
loggerr-1.1.0.dist-info/WHEEL
loggerr-1.1.0.dist-info/top_level.txt
loggerr-1.1.0.dist-info/RECORD
