Metadata-Version: 2.1
Name: loggerr
Version: 1.1.0
Summary: Zero configuration JSON logger(r)
Home-page: https://github.com/fiverr/python-loggerr
Author: fiverr
Author-email: sre@fiverr.com
License: MIT
Platform: UNKNOWN
Classifier: Programming Language :: Python
Classifier: Operating System :: OS Independent
Requires-Python: >=3
License-File: LICENSE
